FSRLearning/__init__.py
FSRLearning/action.py
FSRLearning/feature_selector.py
FSRLearning/fsrlearning.py
FSRLearning/state.py
FSRLearning-1.0.7.dist-info/LICENSE.txt
FSRLearning-1.0.7.dist-info/METADATA
FSRLearning-1.0.7.dist-info/WHEEL
FSRLearning-1.0.7.dist-info/top_level.txt
FSRLearning-1.0.7.dist-info/RECORD
