Metadata-Version: 2.1
Name: FSRLearning
Version: 1.0.7
Summary: The first feature selection method based on reinforcement learning - Python library available on pip for a fast deployment.
Home-page: https://github.com/blefo/FSRLearning
Author: Baptiste Lefort
Author-email: lefort.baptiste@icloud.com
License: MIT
Keywords: feature,selection,reinforcement learning,large dataset,ai
Classifier: Programming Language :: Python :: 3
Classifier: License :: OSI Approved :: MIT License
Classifier: Operating System :: OS Independent
License-File: LICENSE.txt
Requires-Dist: matplotlib
Requires-Dist: numpy
Requires-Dist: pandas
Requires-Dist: scikit-learn
Requires-Dist: scipy
Requires-Dist: tqdm
